Metadata-Version: 1.0
Name: english-filters
Version: 1.0.0
Summary: Django template filters for working with English text
Home-page: http://github.com/brightinteractive/english-filters/
Author: Bright Interactive
Author-email: francis@bright-interactive.com
License: BSD
Platform: UNKNOWN
